PineBioML/__init__.py
PineBioML/IO/__init__.py
PineBioML/model/__init__.py
PineBioML/model/utils.py
PineBioML/model/supervised/Classification.py
PineBioML/model/supervised/Regression.py
PineBioML/model/supervised/Survival.py
PineBioML/model/supervised/__init__.py
PineBioML/preprocessing/__init__.py
PineBioML/preprocessing/bagging.py
PineBioML/preprocessing/impute.py
PineBioML/preprocessing/outlier.py
PineBioML/preprocessing/utils.py
PineBioML/report/__init__.py
PineBioML/report/utils.py
PineBioML/selection/Volcano.py
PineBioML/selection/__init__.py
PineBioML/selection/classification.py
PineBioML/selection/regression.py
pinebioml-1.3.0.1.dist-info/licenses/LICENSE
pinebioml-1.3.0.1.dist-info/METADATA
pinebioml-1.3.0.1.dist-info/WHEEL
pinebioml-1.3.0.1.dist-info/top_level.txt
pinebioml-1.3.0.1.dist-info/RECORD
