Metadata-Version: 2.4
Name: PineBioML
Version: 1.3.0.1
Summary: PineBioML is an easy-to-use ML toolkit.
Author: ICMOL
License: MIT
Project-URL: Homepage, https://github.com/ICMOL/PineBioML
Project-URL: Repository, https://github.com/ICMOL/PineBioML
Classifier: Programming Language :: Python :: 3
Classifier: License :: OSI Approved :: MIT License
Classifier: Operating System :: OS Independent
Requires-Python: <3.12,>=3.9
License-File: LICENSE
Requires-Dist: numpy==2.3.5
Requires-Dist: pandas==2.3.3
Requires-Dist: openpyxl
Requires-Dist: xlrd
Requires-Dist: pyxlsb
Requires-Dist: python-calamine
Requires-Dist: xarray
Requires-Dist: tqdm
Requires-Dist: matplotlib
Requires-Dist: seaborn
Requires-Dist: plotly
Requires-Dist: joblib
Requires-Dist: optuna==4.6.0
Requires-Dist: scikit-learn==1.8.0
Requires-Dist: scikit-learn-intelex
Requires-Dist: umap-learn
Requires-Dist: statsmodels
Requires-Dist: xgboost==3.1.3
Requires-Dist: lightgbm==4.6.0
Requires-Dist: catboost==1.2.8
Requires-Dist: pyarrow
Requires-Dist: shap
Dynamic: license-file
